{
  "version": "5.5.0",
  "flags": {},
  "shapes": [
    {
      "label": "000_Dynamic - car",
      "points": [
        [
          1475.0,
          649.0
        ],
        [
          2191.0,
          1077.0
        ]
      ],
      "group_id": null,
      "description": "",
      "shape_type": "rectangle",
      "flags": {},
      "vehicle_flag": {
        "px": 53,
        "flag": "Left Rear"
      },
      "tl_shape": null,
      "mask": null
    },
    {
      "label": "001_Dynamic - truck",
      "points": [
        [
          539.0,
          549.0
        ],
        [
          1060.0,
          840.0
        ]
      ],
      "group_id": null,
      "description": "",
      "shape_type": "rectangle",
      "flags": {},
      "vehicle_flag": {
        "px": 0,
        "flag": "Right Side"
      },
      "tl_shape": [
        0,
        0
      ],
      "mask": null
    },
    {
      "label": "000_Dynamic - car",
      "points": [
        [
          895.0,
          703.0
        ],
        [
          1390.0,
          928.0
        ]
      ],
      "group_id": null,
      "description": "",
      "shape_type": "rectangle",
      "flags": {},
      "vehicle_flag": {
        "px": 24,
        "flag": "Left Rear"
      },
      "tl_shape": null,
      "mask": null
    },
    {
      "label": "001_Dynamic - truck",
      "points": [
        [
          266.0,
          634.0
        ],
        [
          381.0,
          795.0
        ]
      ],
      "group_id": null,
      "description": "",
      "shape_type": "rectangle",
      "flags": {},
      "vehicle_flag": {
        "px": 21,
        "flag": "Right Front"
      },
      "tl_shape": null,
      "mask": null
    },
    {
      "label": "001_Dynamic - truck",
      "points": [
        [
          0.0,
          653.0
        ],
        [
          116.0,
          809.0
        ]
      ],
      "group_id": null,
      "description": "",
      "shape_type": "rectangle",
      "flags": {},
      "vehicle_flag": {
        "px": 84,
        "flag": "Left Front"
      },
      "tl_shape": null,
      "mask": null
    }
  ],
  "imagePath": "REC_20240320_113415_F_001380.jpg",
  "imageData": null,
  "imageHeight": 1440,
  "imageWidth": 2560
}