{
  "version": "5.5.0",
  "flags": {},
  "shapes": [
    {
      "label": "000_Dynamic - car",
      "points": [
        [
          504.0,
          691.0
        ],
        [
          816.0,
          888.0
        ]
      ],
      "group_id": null,
      "description": "",
      "shape_type": "rectangle",
      "flags": {},
      "vehicle_flag": {
        "px": 46,
        "flag": "Right Front"
      },
      "tl_shape": null,
      "mask": null
    },
    {
      "label": "005_Dynamic - bicycle",
      "points": [
        [
          1681.0,
          804.0
        ],
        [
          1758.0,
          876.0
        ]
      ],
      "group_id": null,
      "description": "",
      "shape_type": "rectangle",
      "flags": {},
      "vehicle_flag": {
        "px": 50,
        "flag": "None"
      },
      "tl_shape": null,
      "mask": null
    },
    {
      "label": "302_Lane marking - diamond",
      "points": [
        [
          1215.0,
          849.0
        ],
        [
          1343.0,
          891.0
        ]
      ],
      "group_id": null,
      "description": "",
      "shape_type": "rectangle",
      "flags": {},
      "vehicle_flag": {
        "px": 50,
        "flag": "None"
      },
      "tl_shape": null,
      "mask": null
    },
    {
      "label": "005_Dynamic - bicycle",
      "points": [
        [
          1334.0,
          766.0
        ],
        [
          1383.0,
          819.0
        ]
      ],
      "group_id": null,
      "description": "",
      "shape_type": "rectangle",
      "flags": {},
      "vehicle_flag": {
        "px": 50,
        "flag": "None"
      },
      "tl_shape": null,
      "mask": null
    },
    {
      "label": "300_Lane marking - stop line",
      "points": [
        [
          1461.0,
          887.0
        ],
        [
          1596.0,
          897.0
        ]
      ],
      "group_id": null,
      "description": "",
      "shape_type": "rectangle",
      "flags": {},
      "vehicle_flag": {
        "px": 50,
        "flag": "None"
      },
      "tl_shape": null,
      "mask": null
    },
    {
      "label": "009_Dynamic - pedestrian",
      "points": [
        [
          1170.0,
          759.0
        ],
        [
          1191.0,
          803.0
        ]
      ],
      "group_id": null,
      "description": "",
      "shape_type": "rectangle",
      "flags": {},
      "vehicle_flag": {
        "px": 50,
        "flag": "None"
      },
      "tl_shape": [
        0,
        0
      ],
      "mask": null
    },
    {
      "label": "401_Static - traffic cone",
      "points": [
        [
          1204.0,
          780.0
        ],
        [
          1215.0,
          804.0
        ]
      ],
      "group_id": null,
      "description": "",
      "shape_type": "rectangle",
      "flags": {},
      "vehicle_flag": {
        "px": 50,
        "flag": "None"
      },
      "tl_shape": null,
      "mask": null
    }
  ],
  "imagePath": "QXD7000_REC_2024_08_05_15_17_22_F_000000.jpg",
  "imageData": null,
  "imageHeight": 1440,
  "imageWidth": 2560
}